prezmanifest/__init__.py
prezmanifest/definednamespaces.py
prezmanifest/documentor.py
prezmanifest/labeller.py
prezmanifest/loader.py
prezmanifest/mrr.ttl
prezmanifest/syncer.py
prezmanifest/system-labels.ttl
prezmanifest/utils.py
prezmanifest/validator.py
prezmanifest/cli/__init__.py
prezmanifest/cli/app.py
prezmanifest/cli/console.py
prezmanifest/cli/commands/__init__.py
prezmanifest/cli/commands/document.py
prezmanifest/cli/commands/label.py
prezmanifest/cli/commands/load.py
prezmanifest/cli/commands/sync.py
prezmanifest/cli/commands/validate.py
prezmanifest/cli/commands/event/__init__.py
prezmanifest/cli/commands/event/asb.py
prezmanifest/cli/commands/event/cli.py
prezmanifest/cli/commands/event/rdf_delta.py
prezmanifest/event/__init__.py
prezmanifest/event/asb_client.py
prezmanifest/event/client.py
prezmanifest/event/syncer.py
prezmanifest/validators/bcp.ttl
prezmanifest/validators/geosparql-1.1.ttl
prezmanifest/validators/idn-cp.ttl
prezmanifest/validators/locidp.ttl
prezmanifest/validators/prezmanifest.ttl
prezmanifest/validators/vocpub-5.2.ttl
prezmanifest-1.2.0.dist-info/METADATA
prezmanifest-1.2.0.dist-info/WHEEL
prezmanifest-1.2.0.dist-info/entry_points.txt
prezmanifest-1.2.0.dist-info/licenses/LICENSE
prezmanifest-1.2.0.dist-info/RECORD
