Metadata-Version: 2.4
Name: prezmanifest
Version: 1.2.0
Summary: A Python package that provides a series of functions to work with Prez Manifests.
Author-email: Nicholas Car <nick@kurrawong.ai>
License-Expression: BSD-3-Clause
License-File: LICENSE
Requires-Python: <4.0,>=3.12
Requires-Dist: dateutils>=0.6.12
Requires-Dist: gitpython>=3.1.45
Requires-Dist: kurra>=2.0.5
Requires-Dist: labelify>=0.6.1
Requires-Dist: pyshacl>=0.29.0
Requires-Dist: rdf-delta>=0.2.5
Requires-Dist: rdflib>=7.5.0
Requires-Dist: typer<0.16,>=0.15.1
Provides-Extra: azure
Requires-Dist: azure-servicebus>=7.14.3; extra == 'azure'
